LICENSE
README.md
setup.py
brainanalysistool/WaveAnalysisFun.py
brainanalysistool/WaveletFun.py
brainanalysistool/__init__.py
brainanalysistool/plotting.py
brainanalysistool/preprocessing.py
brainanalysistool.egg-info/PKG-INFO
brainanalysistool.egg-info/SOURCES.txt
brainanalysistool.egg-info/dependency_links.txt
brainanalysistool.egg-info/requires.txt
brainanalysistool.egg-info/top_level.txt