Metadata-Version: 2.1
Name: brainanalysistool
Version: 0.0.4
Summary: Brain/Neuron/Ecog analysis tool
Home-page: https://github.com/RunminGan1218/Brain-analysis-tool
Author: Runmin Gan
Author-email: 354613146@qq.com
License: MIT
Classifier: Intended Audience :: Developers
Classifier: Programming Language :: Python :: 3
Classifier: License :: OSI Approved :: MIT License
Classifier: Operating System :: OS Independent
License-File: LICENSE
